bground/__init__.py
bground/__main__.py
bground/bdata.py
bground/bfunc.py
bground/help.py
bground/iplot.py
bground/ui.py
bground-1.0.6.dist-info/LICENCE
bground-1.0.6.dist-info/METADATA
bground-1.0.6.dist-info/WHEEL
bground-1.0.6.dist-info/top_level.txt
bground-1.0.6.dist-info/RECORD
