Metadata-Version: 2.1
Name: bground
Version: 1.0.6
Summary: Interactive subtraction of background from XY-data
Home-page: https://github.com/mirekslouf/bground/
Author: Mirek Slouf
Author-email: mirek.slouf@gmail.com
License: MIT
Project-URL: Documentation, https://mirekslouf.github.io/bground/
Classifier: Programming Language :: Python :: 3
Classifier: License :: OSI Approved :: MIT License
Classifier: Operating System :: OS Independent
Requires-Python: >=3.6
License-File: LICENCE
